{
    "system":[
        {
            "name":"郭寒军",
            "community":"openEuler Kernel",
            "title":"选型",
            "profile":""
        },
        {
            "name":"魏永明",
            "community":"MiniGui",
            "title":"合璧操作系统的设计思想",
            "profile":"魏永明，获清华大学工学学士、硕士学位。其主持的 MiniGUI 自由软件项目，是国内知名的几大开源软件项目之一，广泛应用于功能手机、数码相框、智能硬件等嵌入式/物联网产品中。魏永明于2002年创立北京飞漫软件有限公司，成功实践了围绕开源软件的双许可证商业模式。魏永明为 Linux 及开源软件在中国的普及和应用做了大量工作，翻译或编著若干技术著作（《Linux 实用教程》、《Linux 设备驱动程序》等）；2013年，鉴于他在开源软件领域做出的突出贡献，被“中国开源软件推进联盟”评选为“开源软件杰出贡献人物”。魏永明于 2018 年 11 月发起 HybridOS 操作系统开源协作项目，2020年8月，提出 HVML 语言并组织开源协作团队开发其参考实现。",
            "desc":"议题简介：HybridOS 的设计思想体现了“服务甚至取悦开发者”这一终极目标。本报告阐述了为实现这一目标而提出的若干创新技术或举措：数据驱动，为开发者提供了低耦合的系统或应用开发模式；低代码开发，降低了开发者的入门门槛；过程开源，为基于开源协作的操作系统开发提供了一个样板；HVML编程语言，为创造完全自主的国产操作系统奠定了基础。本报告还介绍了 HybridOS 的典型应用场景和未来的演进趋势。"
        },
        {
            "name":"郭占鑫",
            "community":"RT-Thread",
            "title":"开源物联网操作系统RT-Thread的发展之路",
            "profile":"郭占鑫，RT-Thread高级工程师，主要负责“开源社区技术”相关的工作，希望可以跟随RT-Thread为开源社区做出更多的贡献。",
            "desc":"首先介绍RT-Thread是什么，应用场景以及一些行业上的应用案例。然后介绍 RT-Thread的生态建设以及其在开源领域做的事情。最后介绍RT-Thread最近在开展的一些工作，如大学计划等。"
        },
        {
            "name":"吴伟",
            "community":"ISCAS",
            "title":"RISC-V",
            "profile":"",
            "desc":""
        },
        {
            "name":"巨震",
            "community":"ROS Navigation 2",
            "title":"导航定位技术剖析",
            "profile":"",
            "desc":""
        }
    ],
    "yun":[
        {
            "name":"蔡灏旻",
            "community":"iSula",
            "title":"容器构建解决方案[[李峰]]",
            "profile":""
        },
        {
            "name":"陈振东",
            "community":"StratoVirt",
            "title":"openEuler 的轻量级虚拟化平台",
            "profile":"",
            "desc":""
        },
        {
            "name":"王为",
            "community":"",
            "title":"开源私有云ZStack的架构设计",
            "profile":"王为，上海云轴核心架构师。负责ZStack 私有云的网络、存储领域多个产品特性的研发，性能工程部 Team Lead。在  OpenStack Summit、Arch Summit 等大会中做过技术分享。参与过多个国内大型云计算建设项目，向 OpenStack、MidoNet、Buildbot 等多个开源项目做过贡献。在 Linux 的网络、存储领域和私有云软件架构设计有着丰富的经验。",
            "desc":"IaaS 产品有几大难题：产品化难、升级难、持续运维难。业界有很多开源私有云产品——CloudStack、OpenStack、OpenNebula 等等，但都并没有完美解决这些问题，为此我们重新设计开发了 ZStack 这个开源云计算项目，并从第一天开始进行开放开源的社区运营。通过全异步无锁、进程内微服务、工作流引擎、级联框架等等方法实现一个更好用、易用产品化的开源云计算引擎。这次分享将会从私有云架构设计常遇到的问题开始，然后介绍 ZStack 的处理方法以及未来 ZStack 在基础架构上还会做哪些尝试。"
        },
        {
            "name":"耿航",
            "community":"ceph",
            "title":"The Future of Storage",
            "profile":"耿航，中国开源云联盟副秘书长，腾讯云TVP（最具价值专家），E企研究院特聘专家顾问，Ceph中国社区负责人，云原生技术联盟专家委员会专家，曾获2019-2020年度国际社区个人贡献奖、2018中国开源云超级人物奖、2018年云计算开源尖峰人物奖、中国开源云联盟2016年度杰出个人等。主要致力于国内云计算、大数据方面的工作，曾参与国家部委、中国铁路的多个私有云项目建设。主导并参与了国内数本云存储相关书籍和标准的编写和校审工作，同时在省级刊物、行业媒体发表过多篇文章。",
            "desc":"通过混合云IT架构无缝上云已成为企业应用新常态，多云数据管理将成为架起本地数据中心和公共云的桥梁，是传统企业客户上云的新路径。本次分享将围绕多云时代下存储发展的新思路，未来场景以及如何统一管理异构存储进行探讨，从而能够帮助用户把数据的价值发挥到最大。"
        },
        {
            "name":"巨震",
            "community":"ROS Navigation 2",
            "title":"导航定位技术剖析",
            "profile":"",
            "desc":""
        }
    ],
    "ai":[
        {
            "name":"杨滔",
            "community":"天元",
            "title":"开源深度学习框架天元",
            "profile":"杨滔毕业于清华大学，2020年加入旷视科技有限公司，任AI市场总监，负责Brain++和MegEngine的生态建设。加入旷视前杨滔在微软工作十四年，负责最新技术在技术生态中推广，对业界主流技术、云平台以及人工智能技术有丰富和全面的积累。",
            "desc":"自开源以来，旷视开源深度学习框架天元从3月的Alpha版本升级到6月的Beta版本、到10月的1.0正式版，期间实现了9次迭代。本议题将以天元的研发历程为背景，阐述天元深度学习框架在训练推理一体、全平台高效支持以及动静结合的训练能力等方面的优势，探讨如何通过开源框架提升人工智能生成力、构建良性的生态、促进人工智能领域的创新。"
        },
        {
            "name":"王海良",
            "community":"春松客服",
            "title":"开源中文语义理解系统 Clause",
            "profile":"王海良，Chatopera联合创始人&CEO，开源爱好者，有很多的开源项目，积极贡献给开源社区。主要仓库https://github.com/chatopera、https://gitee.com/chatopera演讲经历：参加COSCON2019 《Clause，开源的中文语义理解系统》、组织并参加2016年5月21日～22日的Nodejs Live、2015年至2017年每月组织一次Nodejs等技术的线下Party等。",
            "desc":"Chatopera Language Understanding Service，Chatopera 语义理解服务。即Clause，它是帮助企业快速而低成本的获得好用的语义理解服务的系统，让机器更理解人。Clause 是 Chatopera 团队自主研发及使用其他商业友好的开源软件的方式实现的，Clause 为实现企业聊天机器人提供强大的大脑，包括客服、智能问答和自动流程服务。Clause 利用深度学习，自然语言处理和搜索引擎技术，让机器更加理解人。 "
        },
       
        {
            "name":"张立波",
            "community":"ISCAS",
            "title":"",
            "profile":"",
            "desc":""
        },
        {
            "name":"孙金城",
            "community":"Apache Flink",
            "title":"流计算与Python生态的融合 - Apache PyFlink 核心技术揭秘",
            "profile":"孙金城（金竹），2011年加入阿里，9年的阿里工作中，主导过很多内部核心系统，如：阿里集团行为日志，阿里郎，视频转码，文档转换，流计算等云服务。在2016年初开始了解Apache Flink社区，由初期的参与社区开发到后来逐渐主导具体模块的开发，到负责Apache Flink Python API(PyFlink) 的建设。 目前是 阿里巴巴 Tech Lead， Committer for Apache Beam , PMC Member of Apache Flink and Apache IoTDB and Apache Member.",
            "desc":"Apache Flink 是一个在无界和有界数据流上进行有状态计算的分布式框架，在实时数据仓库，机器学习，数据分析，事件驱动等场景广泛应用，为更好的进行生态支持，自Apache Flink 1.9版本开始，在Apache Beam的基础上增加对Python语言的支持。Python作为TOP3的流行语言，在机器学习，科学计算等领域有着广泛的用户群，Python与Flink的结合不仅将Python的丰富生态功能(比如，Pandas)集成到了Flink，而且增强了Python的分布式计算能力，本次分享将为大家细致剖析PyFlink的核心技术。"
        },
        {
            "name":"屈晟",
            "community":"OpenCV",
            "title":"",
            "profile":"",
            "desc":""
        },
        {
            "name":"王龙步",
            "community":"OpenCV",
            "title":"3D 视觉核心数学基础和实践",
            "profile":"",
            "desc":""
        }
    ],
    "bigdata":[
        {
            "name":"孙金城",
            "community":"Apache IoTDB",
            "title":"Apache IoTDB 核心技术剖析",
            "profile":"孙金城（金竹），2011年加入阿里，9年的阿里工作中，主导过很多内部核心系统，如：阿里集团行为日志，阿里郎，视频转码，文档转换，流计算等云服务。在2016年初开始了解Apache Flink社区，由初期的参与社区开发到后来逐渐主导具体模块的开发，到负责Apache Flink Python API(PyFlink) 的建设。 目前是 阿里巴巴 Tech Lead， Committer for Apache Beam , PMC Member of Apache Flink and Apache IoTDB and Apache Member.",
            "desc":"Gartner指出赋能边缘是2020年十大战略技术趋势之一，5G加速IoT领域的发展，物联网设备数据的收集，存储和计算需求与日俱增。Apache IoTDB是物联网时序数据收集、存储、管理与分析为一体的的软件系统。Apache IoTDB作为Apache的2020新晋顶级项目，以其出色的表现得到了Apache的认可！目前Apache IoTDB与Hadoop、Spark和Flink等进行了深度集成，可以完全胜任工业物联网领域的海量数据存储、高速数据读取和复杂数据分析的需求。本次分享将为大家对Apache IoTDB的前世今生和核心的技术进行详细介绍。 "
        },
        {
            "name":"许利杰",
            "community":"ISCAS",
            "title":"",
            "profile":"",
            "desc":""
        },
       
        {
            "name":"向新勇",
            "community":"openGauss",
            "title":"",
            "profile":"",
            "desc":""
        }

    ],
    "distributedsystem":[
        {
            "name":"潘娟",
            "community":"Apache ShardingSphere",
            "title":"分布式数据库生态圈架构演进",
            "profile":"潘娟，京东数科高级DBA&Apache ShardingSphere PMC，主要负责京东数科分布式数据库开发、数据库运维自动化平台开发等工作。曾负责京东数科数据库自动化平台设计与开发，现专注于Apache ShardingSphere分布式数据库中间件平台的研发。主要在分布式数据库、开源、分布式架构等相关领域进行探索。多次受邀参加数据库&架构领域的相关会议并进行分享交流。",
            "desc":"作为Apache顶级项目的ShardingSphere，将会在最新发布版本中迈向从分布式数据库中间件生态圈到分布式数据库的转型。 已在GitHub上收获12k+ Star的人气分布式数据库中间件生态圈项目将进一步根据领域发展趋势和真实应用场景， 通过数据库化的架构演进，全力打造更为简单、丰富、一体化、可插拔的分布式数据库产品体系， 从而为用户提供最简单易用、功能强大、性能稳定的分布式数据库化产品。 本次分享将详细阐述Apache ShardingSphere数据库化演进中的架构变迁、产品特性、极简落地方案实践等核心内容。"
        },
        {
            "name":"王璞",
            "community":"Datenlord",
            "title":"",
            "profile":"",
            "desc":""
        },
       
        {
            "name":"罗杨",
            "community":"Casbin",
            "title":"基于微服务的访问控制实现企业权限安全",
            "profile":"罗杨，Casbin开源社区创始人、Npcap作者、Nmap开源社区成员，2020年度Google开源贡献奖获得者，北京大学博士，现任微软亚洲研究院研究员。",
            "desc":"随着微服务技术的发展，Web、App和企业软件的权限管理对数据安全至关重要。Casbin是业界主流的开源访问控制框架，致力于帮助复杂系统解决权限管理的难题。其表达能力强大、执行高效，被Intel、VMware、IBM、腾讯云、SpaceX等多个大型企业部署使用，支持Go、Java、Python、C++、.NET、Rust等9种语言，在GitHub上合计已有10000+ stars。"
        }


    ],
    "culture":[
        {
            "name":"庄表伟",
            "community":"",
            "title":"开源治理与数字化转型",
            "profile":"",
            "desc":""
        },
        {
            "name":"温铭",
            "community":"",
            "title":"Apache APISIX 的开源和商业化之路",
            "profile":"温铭，支流科技联合创始人＆CEO，Apache APISIX 项目 VP， Apache Skywalking committer，TARS微服务基金会TOC成员，腾讯云TVP，《OpenResty从入门到实战》专栏作者，前360开源委员会发起人，OpenResty软件基金会首任主席。",
            "desc":"Apache APISIX 是 2019 年 4 月份开始从头开发，6 月份开源，10 月份进入 Apache 孵化器，并在 2020 年 7 月毕业成为 Apache 顶级项目，是最快从 Apache 孵化器毕业的中国项目。 同时，Apache APISIX 背后的公司也在摸索在中国如何做开源项目的商业化，已经有了多家世界 500 强的付费用户。 在这个分享中，温铭会给我们带来 Apache APISIX 在开源以及商业化上的一些实践和思考，希望能让更多的中国开发者来参与和贡献开源。"
        },
       
        {
            "name":"李卓桓",
            "community":"",
            "title":"Wechaty 的开源之路",
            "profile":"李卓桓，微软人工智能最具价值专家（AI MVP）。清华大学本科，中欧国际工商学院EMBA，北京邮电大学计算机系博士在读。现任PreAngel合伙人，Plug and Play Venture Partner，关注钟子期AI创业项目。zixia BBS、叽歪网创始人，曾任优酷网首席科学家、水木清华BBS站长，ChinaRen系统工程师。拥有丰富的互联网创业投资和编程经验，著有《Linux网络编程》《反垃圾邮件完全手册》《智能对话与深度学习》《Chatbot从0到1》《简明的 TensorFlow 2》等技术图书。2016 年在 GitHub 发布基于 Apache-2.0 许可证的 Conversational SDK Wechaty 开源项目，现有数十位 Committers，百余位 Contributors ，并被近万名 GitHub 开发者 Star 。",
            "desc":"Conversational SDK Wechaty 2016 年发布于 GitHub，是一个基于 Apache-2.0 许可证的开源项目。经过4年多的发展，现在 Wechaty 开源社区已经拥有数十位 Committers，百余位 Contributors ，并被近万名 GitHub 开发者 Star 。使用 Wechaty 的开发者已覆盖数万人，并拥有基于微信群的数千人活跃开发者群。Wechaty 社区的 Contributors 遍布全球多个国家地区，和各大互联网公司，职业背景从程序员到设计师，从大学教授到创业者，非常多样化。GitHub 上有千余个开源项目基于 Wechaty 构建了聊天机器人，这些开发者用户也极大地促进了社区的活跃和发展。Wechaty自身对代码质量的管理，使用了 GitHub Actions 的 DevOps 工具完成了 CI/CD 工作流，从自动化单元测试到自动打包集成测试，从自动发布 NPM 包到自动构建和发布对应版本的 Docker Image ，实现了全自动的社区代码发布，极大的提高了社区的协同效率。在开源社区管理上，Wechaty 遵循 The Apache Way ，拥有 PMC / Committer 管理制度，和完善的 Issue / PR / Release 等管理制度。截止2020年，Wechaty 已经有近百万次 NPM 安装下载，并由社区自发推动了 Python, Go, Java, Scala, CSharp, PHP 等语言的适配和发布，是国内最活跃的 Conversational AI Chatbot 开发者社区。"
        },
        {
            "name":"高琨",
            "community":"",
            "title":"开源合规方面议题",
            "profile":"",
            "desc":""
        }


    ],
    "education":[
        {
            "name":"李岗",
            "community":"DolphinScheduler",
            "title":"大学生如何参与开源项目",
            "profile":"李岗、易观大数据平台技术专家，负责大数据基础组件的研发工作，多年大数据开发及平台建设经验. Apache DolphinScheduler(Incubator) PPMC、Apache Local Community Beijing Member.",
            "desc":"今年暑期通过参与开源软件供应链点亮计划，看到了大学生对于开源的热情以及优秀的开发能力和协作能力， 我将以Apache DolphinScheduler社区为例，分享一些大学生如何更快的融入到开源社区的一些经验：社区交流技巧、代码提交经验。 也会谈一下如何选择适合自己的开源社区做贡献，如何跟着社区的成长而成长，如何通过开源贡献提升自己的能力、名誉，为即将步入职场的自己带上一张闪亮的名片！"
        },
        {
            "name":"林旅强",
            "community":"",
            "title":"开源和教育相关的主题",
            "profile":"",
            "desc":""
        },
       
        {
            "name":"琚致远",
            "community":"Apache APISIX",
            "title":"作为毕业生，我是如何参与开源社区并加入 Apache 基金会的",
            "profile":"琚致远，19年本科毕业于河南师范大学，在校期间，积极地参与到了 freeCodeCamp 中文社区，帮助身边人更好的学习 Web 编程；现在是高性能开源网关项目 Apache APISIX 的 PMC 成员。在 Summer 2020 活动中，也以导师身份带领3位学弟们参与到项目中，帮助他们更好地融入开源氛围。",
            "desc":""
        }


    ]
}